fetchFQfromENA/__init__.py
fetchFQfromENA/get_fq_file.py
fetchFQfromENA/get_fq_meta.py
fetchfqfromena-0.1.3.dist-info/METADATA
fetchfqfromena-0.1.3.dist-info/WHEEL
fetchfqfromena-0.1.3.dist-info/entry_points.txt
fetchfqfromena-0.1.3.dist-info/top_level.txt
fetchfqfromena-0.1.3.dist-info/RECORD
