Metadata-Version: 2.2
Name: fetchFQfromENA
Version: 0.1.3
Summary: Retrieve FASTQ file meta information from ENA and download corresponding data.
Home-page: https://github.com/lixiang117423/fetchFQfromENA
Author: Xiang Li
Author-email: lixiang117423@gmail.com
Requires-Dist: requests
Requires-Dist: pathlib
Requires-Dist: argparse
Dynamic: author
Dynamic: author-email
Dynamic: summary
